{
  "collapse-filter": false,
  "search": "",
  "showTags": true,
  "showAttachments": true,
  "hideUnresolved": true,
  "showOrphans": true,
  "collapse-color-groups": false,
  "colorGroups": [
    {
      "query": "path:\"400 Plants\"",
      "color": {
        "a": 1,
        "rgb": 65280
      }
    },
    {
      "query": "path:\"500 Animals\"",
      "color": {
        "a": 1,
        "rgb": 16711680
      }
    },
    {
      "query": "path:\"9000 Unsorted Notes\"",
      "color": {
        "a": 1,
        "rgb": 7276185
      }
    }
  ],
  "collapse-display": false,
  "showArrow": true,
  "textFadeMultiplier": 0,
  "nodeSizeMultiplier": 1.85352011494253,
  "lineSizeMultiplier": 1,
  "collapse-forces": true,
  "centerStrength": 0.315134099616858,
  "repelStrength": 10,
  "linkStrength": 0.469827586206897,
  "linkDistance": 144,
  "scale": 0.23980143121608194,
  "close": true
}